ipwhl/__init__.py
ipwhl/declck.py
ipwhl/declgen.py
ipwhl/deps.py
ipwhl/depsck.py
ipwhl/misc.py
ipwhl/nameck.py
ipwhl/prefix.py
ipwhl/publish.py
ipwhl/py.typed
ipwhl/tags.py
ipwhl-1.1.0.dist-info/entry_points.txt
ipwhl-1.1.0.dist-info/COPYING
ipwhl-1.1.0.dist-info/WHEEL
ipwhl-1.1.0.dist-info/METADATA
ipwhl-1.1.0.dist-info/RECORD
