Metadata-Version: 2.1
Name: ipwhl
Version: 1.1.0
Summary: Utilities for the InterPlanetary Wheels
Keywords: ipfs,wheel,packaging,toml
Author-email: Nguyễn Gia Phong <mcsinyx@disroot.org>
Maintainer-email: Nguyễn Gia Phong <mcsinyx@disroot.org>, Ngô Ngọc Đức Huy <huyngo@disroot.org>
Requires-Python: >=3.6
Classifier: Development Status :: 5 - Production/Stable
Classifier: Environment :: Console
Classifier: Intended Audience :: Developers
Classifier: License :: OSI Approved :: GNU Affero General Public License v3 or later (AGPLv3+)
Classifier: Operating System :: OS Independent
Classifier: Programming Language :: Python
Classifier: Topic :: System :: Archiving :: Packaging
Classifier: Topic :: Utilities
Requires-Dist: packaging
Requires-Dist: tomli
Project-URL: Source, https://git.sr.ht/~cnx/ipwhl-utils
